LICENSE
README.md
setup.py
atrt/DTPM_calcfunc.py
atrt/__init__.py
atrt/dts_dataprocessing.py
atrt/flowrate_function.py
atrt/thermal_conductivity_function.py
atrt.egg-info/PKG-INFO
atrt.egg-info/SOURCES.txt
atrt.egg-info/dependency_links.txt
atrt.egg-info/requires.txt
atrt.egg-info/top_level.txt
tests/test_basic.py