Metadata-Version: 2.2
Name: atrt
Version: 0.1.0
Summary: Active Temperature Sensing and Thermal Response Test Analysis Package
Home-page: https://github.com/wfyissuperman/atrt
Author: 王丰源
Author-email: wfy22500@smail.nju.edu.cn
Project-URL: Bug Reports, https://github.com/wfyissuperman/atrt/issues
Project-URL: Source, https://github.com/wfyissuperman/atrt
Keywords: thermal conductivity,DTS,temperature sensing,groundwater flow,heat transfer
Classifier: Development Status :: 3 - Alpha
Classifier: Intended Audience :: Science/Research
Classifier: Topic :: Scientific/Engineering :: Physics
Classifier: License :: OSI Approved :: MIT License
Classifier: Programming Language :: Python :: 3
Classifier: Programming Language :: Python :: 3.8
Classifier: Programming Language :: Python :: 3.9
Classifier: Programming Language :: Python :: 3.10
Classifier: Programming Language :: Python :: 3.11
Requires-Python: >=3.8
License-File: LICENSE
Requires-Dist: numpy<2.0.0,>=1.20.0
Requires-Dist: pandas<2.1.0,>=1.3.0
Requires-Dist: scipy>=1.7.0
Requires-Dist: matplotlib<3.9.0,>=3.4.0
Requires-Dist: pytest>=6.0.0
Requires-Dist: pytest-cov>=2.0.0
Requires-Dist: black>=21.0.0
Requires-Dist: flake8>=3.8.0
Dynamic: author
Dynamic: author-email
Dynamic: classifier
Dynamic: description
Dynamic: description-content-type
Dynamic: home-page
Dynamic: keywords
Dynamic: project-url
Dynamic: requires-dist
Dynamic: requires-python
Dynamic: summary
